aweme/__init__.py
aweme/aweme.py
aweme-2.0.0.dist-info/LICENSE
aweme-2.0.0.dist-info/METADATA
aweme-2.0.0.dist-info/WHEEL
aweme-2.0.0.dist-info/entry_points.txt
aweme-2.0.0.dist-info/top_level.txt
aweme-2.0.0.dist-info/RECORD
