Metadata-Version: 2.1
Name: aweme
Version: 2.0.0
Summary: Douyin Command Line Interface
Home-page: https://github.com/maguowei/aweme
Author: maguowei
Author-email: imaguowei@gmail.com
License: MIT
Keywords: Douyin CLI,Douyin API
Platform: any
Classifier: Development Status :: 5 - Production/Stable
Classifier: Environment :: Web Environment
Classifier: Intended Audience :: Developers
Classifier: License :: OSI Approved :: MIT License
Classifier: Operating System :: OS Independent
Classifier: Programming Language :: Python
Classifier: Programming Language :: Python :: 3
Classifier: Programming Language :: Python :: 3.6
Classifier: Programming Language :: Python :: 3.7
Requires-Python: >=3.6
Requires-Dist: requests (==2.22.0)
Requires-Dist: fire (==0.2.1)
